pyflakes-stubs/METADATA.toml
pyflakes-stubs/__init__.pyi
pyflakes-stubs/__main__.pyi
pyflakes-stubs/api.pyi
pyflakes-stubs/checker.pyi
pyflakes-stubs/messages.pyi
pyflakes-stubs/py.typed
pyflakes-stubs/reporter.pyi
pyflakes-stubs/scripts/__init__.pyi
pyflakes-stubs/scripts/pyflakes.pyi
types_pyflakes-3.3.2.20250511.dist-info/licenses/LICENSE
types_pyflakes-3.3.2.20250511.dist-info/METADATA
types_pyflakes-3.3.2.20250511.dist-info/WHEEL
types_pyflakes-3.3.2.20250511.dist-info/top_level.txt
types_pyflakes-3.3.2.20250511.dist-info/RECORD
